lapart/__init__.py
lapart/art.py
lapart/test.py
lapart/train.py
lapart_python-0.1.6.dist-info/METADATA
lapart_python-0.1.6.dist-info/WHEEL
lapart_python-0.1.6.dist-info/top_level.txt
lapart_python-0.1.6.dist-info/RECORD
