Metadata-Version: 2.1
Name: lapart-python
Version: 0.1.6
Summary: Python package for performance monitoring of time series data.
Home-page: https://github.com/sandialabs/lapart-python
Author: LAPART Developers
Maintainer-email: cbjones@sandia.gov
License: Revised BSD
Platform: UNKNOWN
Requires-Dist: numpy (>=1.10.4)
Requires-Dist: pandas (>=0.18.0)
Requires-Dist: matplotlib
